cubetools/__init__.py
cubetools/download_model.py
cubetools/huggingface.py
cubetools/huggingface2.py
cubetools/image_tools.py
cubetools/mindspore_lite_predict.py
cubetools/modelers.py
cubetools/modelers2.py
cubetools/modelscope.py
cubetools/modelscope2.py
cubetools/onnx_predict.py
cubetools/openvino_predict.py
cubetools/paddle_predict.py
cubetools/python_chat_frontend.py
cubetools/python_video_frontend.py
cubetools/pytorch_predict.py
cubetools/torch_predict.py
cubetools/video_capture.py
cubetools/video_predict.py
cubetools/video_predict2.py
cubetools/yolo_predictor.py
cubetools/yolo_process.py
cubetools-0.9.0.dist-info/METADATA
cubetools-0.9.0.dist-info/WHEEL
cubetools-0.9.0.dist-info/entry_points.txt
cubetools-0.9.0.dist-info/top_level.txt
cubetools-0.9.0.dist-info/RECORD
